sv/__init__.py
sv/config_samples/__init__.py
sv/config_samples/default_cfg.py
sv/libs/__init__.py
sv/libs/core/__init__.py
sv/libs/core/base_metrics.py
sv/libs/core/criterion.py
sv/libs/core/infer.py
sv/libs/core/lr_scheduler.py
sv/libs/core/trainer.py
sv/libs/data/__init__.py
sv/libs/data/dataset/__init__.py
sv/libs/data/dataset/dataset.py
sv/libs/data/dataset/joint_transforms.py
sv/libs/data/pre_process/__init__.py
sv/libs/data/pre_process/dilated_crop.py
sv/libs/data/pre_process/slide_win_crop.py
sv/libs/scripts/__init__.py
sv/libs/scripts/mix_train.py
sv/libs/scripts/test.py
sv/libs/tools/__init__.py
sv/libs/tools/color_palette.py
sv/libs/tools/init_weight.py
sv/libs/tools/stitch_probs.py
sv/libs/tools/utils.py
sv/modules/__init__.py
sv/modules/multi_scale.py
sv/modules/packaged_conv.py
sv/modules/seg_modules.py
sv/modules/attention/__init__.py
sv/modules/attention/cbam.py
sv/modules/attention/dran.py
sv/modules/attention/dual_att.py
sv/modules/attention/gate_att.py
sv/modules/attention/se_block.py
sv/modules/attention/self_att.py
sv/modules/attention/sk_block.py
sv/modules/backbones/__init__.py
sv/modules/backbones/ddrnet_23_slim.py
sv/modules/backbones/mfnet.py
sv/modules/backbones/shufflenet_v2.py
sv/modules/backbones/stdcnet.py
sv/modules/backbones/vgg16.py
sv/modules/backbones/hrnet/__init__.py
sv/modules/backbones/hrnet/hrnet.py
sv/modules/backbones/hrnet/hrnet_config.py
sv/modules/backbones/mobilenet/__init__.py
sv/modules/backbones/mobilenet/mobilenet_v2.py
sv/modules/backbones/mobilenet/mobilenet_v3.py
sv/modules/backbones/rep_vgg/__init__.py
sv/modules/backbones/rep_vgg/convert.py
sv/modules/backbones/rep_vgg/rep_vgg.py
sv/modules/backbones/resnet/__init__.py
sv/modules/backbones/resnet/dilated_resnet.py
sv/modules/backbones/resnet/ori_resnet.py
sv/modules/backbones/resnet/resnet18_d.py
sv/modules/baseline/__init__.py
sv/modules/baseline/unet.py
sv_seg-1.1.dist-info/LICENSE.txt
sv_seg-1.1.dist-info/METADATA
sv_seg-1.1.dist-info/WHEEL
sv_seg-1.1.dist-info/top_level.txt
sv_seg-1.1.dist-info/RECORD
